{"notes_build tools_esbuild_03_faqs.md":"8669bd71","notes_build tools_esbuild_index.md":"08161139","notes_build tools_parcel_01_pre.md":"55a51264","posts_vitepress_001_vitepress.md":"320ea87a","notes_build tools_rollup_index.md":"1d6755f5","notes_build tools_rollup_04_faqs.md":"252220fa","posts_node_006_pm2.md":"16f588fb","notes_build tools_esbuild_01_pre.md":"b2baeeeb","notes_build tools_esbuild_02_use.md":"0c842912","notes_build tools_rollup_02_use.md":"de1e7894","notes_build tools_rollup_03_plugins.md":"eb2f95f0","posts_node_007_mongodb.md":"1d579172","posts_node_004_nginx.md":"a12b05fd","posts_pits_001_deploy-gitpage-jekyll.md":"bb9d8f33","posts_pits_002ubuntu-install-mongodb.md":"b81a2981","posts_tips_001_color-consolelog.md":"d8b957ca","posts_tips_002_judge-mobile.md":"2b52a596","posts_vitepress_002_vitepress-theme-mochi.md":"ff1d2ecd","posts_vue_001-source-optimization.md":"06f2b98f","projects_index.md":"57ce33d1","category.md":"eda0c600","index.md":"0e20ad2a","origin.md":"e1908c2d","tag.md":"11b268b3","timeline.md":"afae7d08","notes_build tools_rollup_01_pre.md":"0a48b4c6","posts_node_005_koa-basic.md":"28845604","posts_node_002_npm.md":"68861916","posts_node_001_node-basic.md":"196c36b9","posts_node_003_npx.md":"42c5366a"}
