{"notes_build tools_esbuild_index.md":"d0d83382","notes_build tools_parcel_01_pre.md":"f4032b34","notes_build tools_rollup_01_pre.md":"6dc06351","notes_build tools_rollup_03_plugins.md":"35091605","notes_soul torture_javascript_003_tear-code.md":"72b1548c","notes_soul torture_javascript_004_advanced.md":"32e1adbc","notes_soul torture_node_001_basic.md":"8c2e73e6","notes_soul torture_sublimation_001_comprehensive.md":"77d89159","notes_soul torture_vue_001_basic.md":"e45444f3","notes_vue3 migration_component_001_functional-components.md":"02dfd16e","notes_build tools_rollup_04_faqs.md":"d101dace","notes_soul torture_javascript_001_basic.md":"41e23f61","notes_build tools_rollup_02_use.md":"f2ad5fd2","notes_build tools_esbuild_03_faqs.md":"93af82bb","notes_build tools_esbuild_01_pre.md":"e5b9a10a","notes_build tools_esbuild_02_use.md":"6f43ee67","notes_build tools_rollup_index.md":"dae135b7","notes_vue3 migration_component_002_async-components.md":"6742c7f4","notes_vue3 migration_component_003_emits-option.md":"fb7ed9b9","posts_javascript_010_cross-domain.md":"edb8af49","notes_soul torture_css_001_basic.md":"f799eec3","notes_soul torture_javascript_002_dom bom.md":"6d81aade","notes_vue3 migration_guide_001_pre.md":"ac5450e2","notes_vue3 migration_render function_001_render-function-api.md":"e26ae8d1","notes_vue3 migration_render function_002_slots-unification.md":"89c82553","notes_vue3 migration_render function_003_listeners-removed.md":"55e1c2ac","notes_vue3 migration_render function_004_attrs-includes-class-style.md":"bfe74637","notes_vue3 migration_template directives_001_v-model.md":"5715836f","notes_vue3 migration_template directives_002-key-attribute.md":"5d02ceb0","notes_vue3 migration_template directives_003_v-if-v-for.md":"167d0874","notes_vue3 migration_template directives_004_v-bind.md":"6daa0670","notes_vue3 migration_template directives_005_v-on-native-modifier-removed.md":"1f2fb417","posts_http_001_http.md":"93a840a1","posts_http_002_http-cache.md":"17ba84e6","posts_javascript_001_special-value.md":"4c9d40b6","posts_javascript_002_numeric-conversion.md":"00667a4b","posts_javascript_003_basic-grammar.md":"2f0833aa","posts_javascript_004_traverse.md":"bf50e69f","posts_javascript_005_event-loop.md":"8fca175b","posts_javascript_006_promise.md":"a544c349","posts_javascript_008_ajax.md":"c5a58379","posts_javascript_009_fetch.md":"53835cd4","posts_node_001_node-basic.md":"68220169","posts_node_002_npm.md":"976ab49d","posts_node_003_npx.md":"8d506acb","posts_vue_001-vue3-optimization.md":"0ebb2b41","posts_vue_002_compiler.md":"698eedab","posts_vue_004_vue3-reactive-source.md":"1ec37825","projects_index.md":"478bee95","index.md":"818a0f9c","origin.md":"e0e93d4a","tag.md":"a1f4efdc","timeline.md":"2a0ae087","posts_javascript_007_handwriting-promise.md":"d02608cd","category.md":"2ea44576","posts_pits_001_deploy-gitpage-jekyll.md":"55fccfeb","posts_pits_002ubuntu-install-mongodb.md":"e59a297a","posts_tips_002_judge-mobile.md":"1184f770","posts_vitepress_001_vitepress.md":"2888c906","posts_vitepress_002_vitepress-theme-mochi.md":"965f325e","posts_vitepress_003_algolia.md":"12005e1d","posts_node_005_koa-basic.md":"520928ec","posts_node_007_mongodb.md":"964aeb82","posts_node_004_nginx.md":"54a13eac","posts_tips_001_color-consolelog.md":"1759dea7","posts_node_006_pm2.md":"f9f0e371"}
